chropy/__init__.py
chropy/example.py
chropy-0.0.1.dist-info/LICENSE
chropy-0.0.1.dist-info/METADATA
chropy-0.0.1.dist-info/WHEEL
chropy-0.0.1.dist-info/top_level.txt
chropy-0.0.1.dist-info/RECORD
