Metadata-Version: 2.1
Name: chropy
Version: 0.0.1
Summary: Python scripts to help with Chroma (lattice QCD)
Author-email: Joshua Lin <joshua.z.lin@gmail.com>
License: MIT License        
Project-URL: Homepage, https://github.com/pypa/sampleproject
Project-URL: Bug Tracker, https://github.com/pypa/sampleproject/issues
Classifier: Programming Language :: Python :: 3
Classifier: License :: OSI Approved :: MIT License
Classifier: Operating System :: OS Independent
Requires-Python: >=3.7
License-File: LICENSE
